constants.py
ackerman-0.1.0.dist-info/licenses/LICENSE
ackerman-0.1.0.dist-info/METADATA
ackerman-0.1.0.dist-info/WHEEL
ackerman-0.1.0.dist-info/entry_points.txt
ackerman-0.1.0.dist-info/top_level.txt
ackerman-0.1.0.dist-info/RECORD
